fido/__init__.py
fido/char_handler.py
fido/fido.py
fido/package.py
fido/prepare.py
fido/toxml.py
fido/update_signatures.py
fido/versions.py
fido/conf/DROID_SignatureFile-v109.xml
fido/conf/container-signature-20200121.xml
fido/conf/dc.xsd
fido/conf/dcmitype.xsd
fido/conf/dcterms.xsd
fido/conf/fido-formats.xsd
fido/conf/format_extension_template.xml
fido/conf/format_extensions.xml
fido/conf/formats-v109.xml
fido/conf/pronom-xml-v109.zip
fido/conf/versions.xml
fido/pronom/__init__.py
fido/pronom/http.py
fido/pronom/soap.py
opf_fido-1.6.1.dist-info/LICENSE.txt
opf_fido-1.6.1.dist-info/METADATA
opf_fido-1.6.1.dist-info/WHEEL
opf_fido-1.6.1.dist-info/entry_points.txt
opf_fido-1.6.1.dist-info/top_level.txt
opf_fido-1.6.1.dist-info/RECORD
